addition/__init__.py
addition/sum.py
subtraction/__init__.py
subtraction/sub.py
myvtslib-2.0.dist-info/METADATA
myvtslib-2.0.dist-info/WHEEL
myvtslib-2.0.dist-info/top_level.txt
myvtslib-2.0.dist-info/RECORD
