Metadata-Version: 2.1
Name: myvtslib
Version: 2.0
Summary: Arth operations
Author: VTS
License: MIT
